<annotation>
    <folder>images</folder>
    <filename>238.jpg</filename>
    <size>
        <width>640</width>
        <height>480</height>
        <depth>3</depth>
    </size>
    <object>
        <name>zhen_kong</name>
        <pose>Unspecified</pose>
        <truncated>0</truncated>
        <difficult>0</difficult>
        <bndbox>
            <xmin>256</xmin>
            <ymin>272</ymin>
            <xmax>302</xmax>
            <ymax>321</ymax>
        </bndbox>
    </object>
    <object>
        <name>zhen_kong</name>
        <pose>Unspecified</pose>
        <truncated>0</truncated>
        <difficult>0</difficult>
        <bndbox>
            <xmin>294</xmin>
            <ymin>288</ymin>
            <xmax>328</xmax>
            <ymax>329</ymax>
        </bndbox>
    </object>
    <object>
        <name>zang_wu</name>
        <pose>Unspecified</pose>
        <truncated>0</truncated>
        <difficult>0</difficult>
        <bndbox>
            <xmin>212</xmin>
            <ymin>329</ymin>
            <xmax>318</xmax>
            <ymax>423</ymax>
        </bndbox>
    </object>
</annotation>